{"title": "Republic of the Sudan", "Capital and largest city": "Khartoum", "Official languages": "Arabic , English", "": "Sudanese Arabic", "Ethnic groups": ["70% Sudanese Arab", "5.5% Beja", "2.5% Nuba", "2% Fur", "2% Egyptian", "1% Hausa", "0.5% Fulani", "17.3% other"], "Religion (2020)": ["97% Sunni Islam", "1.5% Christianity", "1.5% Traditional Faiths", "0.9% Others"], "Demonym(s)": "Sudanese", "Government": "Federal republic under a military junta", "• Transitional Sovereignty Council": ["Abdel Fattah al-Burhan (Chairman)", "Malik Agar (Deputy chairman)"], "• Prime Minister": ["Osman Hussein (acting)"], "Legislature": "Vacant", "• Kingdom of Kerma": "2500 BC", "• Kingdom of Kush": "1070 BC", "• Makuria , Nobatia , and Alodia": "c.", "• Tunjur , Funj , and Darfur Sultanates": "c.", "• Turco-Egyptian Sudan": "1820", "• Mahdist State": "1885", "• Anglo-Egyptian Condominium": "1899", "• Independence": "1 January 1956", "• Democratic Republic of Sudan": "25 May 1969", "• Republic of Sudan (1985–2019)": "6 April 1985", "• Secession of South Sudan": "9 July 2011", "• Sudanese Revolution": "19 December 2018", "• 2019 Draft Constitutional Declaration effective": "20 August 2019", "• 2023 Sudan conflict": "15 April 2023", "• Total": "$25.569 billion ( 96th )", "• 2023 estimate": "49,197,555 ( 30th )", "• Density": "21.3/km (55.2/sq mi) ( 202nd )", "GDP": "2023 estimate", "• Per capita": "$533 ( 171st )", "Gini": "34.2", "HDI": "0.508 · 172nd", "Currency": "Sudanese pound ( SDG )", "Time zone": "( CAT )", "Date format": "dd/mm/yyyy", "Driving side": "right", "Calling code": "+249", "ISO 3166 code": "SD", "Internet TLD": ".sd سودان."}