{"title": "Republic of Equatorial Guinea", "Capital": "Malabo ( current ) Ciudad de la Paz ( under construction )", "Largest city": "Bata", "Official languages": ["Spanish", "French", "Portuguese"], "": ["Fang", "Bube", "Annobonese Creole", "Kombe", "Kwasio"], "Ethnic groups (2020 )": ["85.7% Fang", "6.5% Bubi", "3.6% Ndowe", "1.6% Annobon", "1.1% Bujeba", "1.1% other"], "Religion (2020)": ["88.7% Christianity", "5.0% no religion", "4.0% Islam", "1.7% traditional faiths", "0.6% others"], "Demonym(s)": ["Equatoguinean", "Equatorial Guinean"], "Government": "Unitary dominant-party presidential republic under a dictatorship", "• President": "Teodoro Obiang Nguema Mbasogo", "• Vice President": "Teodoro Nguema Obiang Mangue", "• Prime Minister": "Manuela Roka Botey", "Legislature": "Parliament", "• Upper house": "Senate", "• Lower house": "Chamber of Deputies", "• Declared": "12 October 1968", "• Total": "$16.012 billion ( 133rd )", "• Water (%)": "negligible", "• 2022 estimate": "1,679,172 ( 154th )", "GDP": "2022 estimate", "• Per capita": "$8,462", "HDI": "0.596 · 145th", "Currency": "Central African CFA franc ( XAF )", "Time zone": "( WAT )", "Date format": "dd/mm/yyyy", "Driving side": "right", "Calling code": "+240", "ISO 3166 code": "GQ", "Internet TLD": ".gq"}