{"title": "Saint Vincent and the Grenadines", "Capital and largest city": "Kingstown", "Official languages": "English", "Vernacular language": "Vincentian Creole", "Ethnic groups (2020)": ["66% Black (African)", "19% Mixed", "6% Indian", "4% European", "2% Kalinago", "3% others"], "Religion (2020)": ["88.6% Christianity", "—70.2% Protestantism", "—18.4% other Christian", "3.4% Hinduism", "2.5% no religion", "1.8% Rastafarianism", "1.6% Baha'i faith", "1.5% Islam", "0.6% others"], "Demonym(s)": "Vincentian and Grenadinian Vincy (colloquial)", "Government": "Unitary parliamentary constitutional monarchy", "• Monarch": "Charles III", "•": "Susan Dougan", "• Prime Minister": "Ralph Gonsalves", "Legislature": "House of Assembly", "• Associated State": "27 October 1969", "• from the United Kingdom": "27 October 1979", "• Total": "$864 million", "• Water (%)": "negligible", "• 2022 estimate": "110,872 ( 180th )", "• 2012 census": "109,991", "• Density": "307/km (795.1/sq mi) ( 39th )", "GDP": "2019 estimate", "• Per capita": "$7,827", "HDI": "0.751 · 89th", "Currency": "E.C dollar ( XCD )", "Time zone": "( AST )", "Driving side": "left", "Calling code": "+1 784", "ISO 3166 code": "VC", "Internet TLD": ".vc"}